{
	"_comment": "DO NOT CHANGE THE ORDER OF CHARACTERS. ANIMALS MUST REMAIN AT TOP OF JSON AND IN ORDER",
	"objects": [
		{
			"_id": 0,
			"active": true,
			"client": {
				"fragShaderPath": "../resources/shaders/material.frag",
				"isTransparent": false,
				"modelPath": "../resources/objects/chicken/Chicken.obj",
				"vertShaderPath": "../resources/shaders/material.vert"
			},
			"level": "ALL",
			"name": "Chicken",
			"server": {
				"colliders": [
					{
						"center": {
							"x": 0.002,
							"y": 0.677,
							"z": 0.141
						},
						"halfExtents": {
							"x": 0.25,
							"y": 0.25,
							"z": 0.25
						},
						"isTrigger": false,
						"orientation": {
							"forward": {
								"x": 0.0,
								"y": 0.0,
								"z": 3.0
							},
							"right": {
								"x": 3.0,
								"y": 0.0,
								"z": 0.0
							},
							"up": {
								"x": 0.0,
								"y": 3.0,
								"z": 0.0
							}
						}
					}
				],
				"interaction": "NONE",
				"static": false
			},
			"transform": {
				"position": {
					"x": 5.627,
					"y": 0.866,
					"z": -3.0
				},
				"rotation": {
					"x": 0.0,
					"y": 0.0,
					"z": 0.0
				},
				"scale": {
					"x": 3.0,
					"y": 3.0,
					"z": 3.0
				}
			}
		},
		{
			"_id": 1,
			"active": true,
			"client": {
				"fragShaderPath": "../resources/shaders/material.frag",
				"isTransparent": false,
				"modelPath": "../resources/objects/Pig/Pig.obj",
				"vertShaderPath": "../resources/shaders/material.vert"
			},
			"level": "ALL",
			"name": "Pig",
			"server": {
				"colliders": [
					{
						"center": {
							"x": 0.0,
							"y": 1.25,
							"z": -0.012
						},
						"halfExtents": {
							"x": 0.308,
							"y": 0.5,
							"z": 0.576
						},
						"isTrigger": false,
						"orientation": {
							"forward": {
								"x": 0.0,
								"y": 0.0,
								"z": 2.5
							},
							"right": {
								"x": 2.5,
								"y": 0.0,
								"z": 0.0
							},
							"up": {
								"x": 0.0,
								"y": 2.5,
								"z": 0.0
							}
						}
					}
				],
				"interaction": "NONE",
				"static": false
			},
			"transform": {
				"position": {
					"x": -2.0,
					"y": 0.9,
					"z": -3.0
				},
				"rotation": {
					"x": 0.0,
					"y": 0.0,
					"z": 0.0
				},
				"scale": {
					"x": 2.5,
					"y": 2.5,
					"z": 2.5
				}
			}
		},
		{
			"_id": 2,
			"active": true,
			"client": {
				"fragShaderPath": "../resources/shaders/material.frag",
				"isTransparent": false,
				"modelPath": "../resources/objects/Sheep/Sheep.obj",
				"vertShaderPath": "../resources/shaders/material.vert"
			},
			"level": "ALL",
			"name": "Sheep",
			"server": {
				"colliders": [
					{
						"center": {
							"x": 0.0,
							"y": 1.538,
							"z": 0.132
						},
						"halfExtents": {
							"x": 0.52,
							"y": 0.615,
							"z": 0.67
						},
						"isTrigger": false,
						"orientation": {
							"forward": {
								"x": 0.0,
								"y": 0.0,
								"z": 2.5
							},
							"right": {
								"x": 2.5,
								"y": 0.0,
								"z": 0.0
							},
							"up": {
								"x": 0.0,
								"y": 2.5,
								"z": 0.0
							}
						}
					}
				],
				"interaction": "NONE",
				"static": false
			},
			"transform": {
				"position": {
					"x": 2.0,
					"y": 0.9,
					"z": -3.0
				},
				"rotation": {
					"x": 0.0,
					"y": 0.0,
					"z": 0.0
				},
				"scale": {
					"x": 2.5,
					"y": 2.5,
					"z": 2.5
				}
			}
		},
		{
			"_id": 3,
			"active": true,
			"client": {
				"fragShaderPath": "../resources/shaders/material.frag",
				"isTransparent": false,
				"modelPath": "../resources/objects/cow/Cow.obj",
				"vertShaderPath": "../resources/shaders/material.vert"
			},
			"level": "ALL",
			"name": "Cow",
			"server": {
				"colliders": [
					{
						"center": {
							"x": 0.0,
							"y": 1.705,
							"z": -0.205
						},
						"halfExtents": {
							"x": 0.361,
							"y": 0.682,
							"z": 0.806
						},
						"isTrigger": false,
						"orientation": {
							"forward": {
								"x": 0.0,
								"y": 0.0,
								"z": 2.5
							},
							"right": {
								"x": 2.5,
								"y": 0.0,
								"z": 0.0
							},
							"up": {
								"x": 0.0,
								"y": 2.5,
								"z": 0.0
							}
						}
					}
				],
				"interaction": "NONE",
				"static": false
			},
			"transform": {
				"position": {
					"x": -4.989,
					"y": 1.093,
					"z": -2.852
				},
				"rotation": {
					"x": 0.0,
					"y": 0.0,
					"z": 0.0
				},
				"scale": {
					"x": 2.5,
					"y": 2.5,
					"z": 2.5
				}
			}
		},{
			"_id": 0,
			"active": true,
			"client": {
				"fragShaderPath": "../resources/shaders/material.frag",
				"isTransparent": false,
				"modelPath": "../resources/objects/chickencoop/ChickenCoop.obj",
				"vertShaderPath": "../resources/shaders/material.vert"
			},
			"level": "PENS",
			"name": "ChickenCoop",
			"server": {
				"colliders": [
					{
						"center": {
							"x": 6.381,
							"y": 0.0,
							"z": -0.538
						},
						"halfExtents": {
							"x": 139.122,
							"y": 0.5,
							"z": 17.843
						},
						"isTrigger": false,
						"orientation": {
							"forward": {
								"x": 0.0,
								"y": 0.0,
								"z": 1.422
							},
							"right": {
								"x": 0.368,
								"y": 0.0,
								"z": 0.0
							},
							"up": {
								"x": 0.0,
								"y": 1.011,
								"z": 0.0
							}
						}
					},
					{
						"center": {
							"x": -44.026,
							"y": 3.438,
							"z": -0.377
						},
						"halfExtents": {
							"x": 3.026,
							"y": 55.322,
							"z": 35.85
						},
						"isTrigger": false,
						"orientation": {
							"forward": {
								"x": 0.0,
								"y": 0.0,
								"z": 1.0
							},
							"right": {
								"x": 1.0,
								"y": 0.0,
								"z": 0.0
							},
							"up": {
								"x": 0.0,
								"y": 1.0,
								"z": 0.0
							}
						}
					},
					{
						"center": {
							"x": 48.285,
							"y": 18.839,
							"z": 0.0
						},
						"halfExtents": {
							"x": 1.875,
							"y": 40.515,
							"z": 51.268
						},
						"isTrigger": false,
						"orientation": {
							"forward": {
								"x": 0.0,
								"y": 0.0,
								"z": 1.0
							},
							"right": {
								"x": 1.0,
								"y": 0.0,
								"z": 0.0
							},
							"up": {
								"x": 0.0,
								"y": 1.0,
								"z": 0.0
							}
						}
					},
					{
						"center": {
							"x": 17.785,
							"y": 17.053,
							"z": -21.741
						},
						"halfExtents": {
							"x": 33.649,
							"y": 45.349,
							"z": 0.657
						},
						"isTrigger": false,
						"orientation": {
							"forward": {
								"x": 0.0,
								"y": 0.0,
								"z": 1.0
							},
							"right": {
								"x": 1.0,
								"y": 0.0,
								"z": 0.0
							},
							"up": {
								"x": 0.0,
								"y": 1.0,
								"z": 0.0
							}
						}
					},
					{
						"center": {
							"x": 18.608,
							"y": 15.469,
							"z": 22.735
						},
						"halfExtents": {
							"x": 33.746,
							"y": 45.0,
							"z": 0.874
						},
						"isTrigger": false,
						"orientation": {
							"forward": {
								"x": 0.0,
								"y": 0.0,
								"z": 1.0
							},
							"right": {
								"x": 1.0,
								"y": 0.0,
								"z": 0.0
							},
							"up": {
								"x": 0.0,
								"y": 1.0,
								"z": 0.0
							}
						}
					},
					{
						"center": {
							"x": 3.096,
							"y": 10.251,
							"z": 0.898
						},
						"halfExtents": {
							"x": 22.147,
							"y": 0.5,
							"z": 11.598
						},
						"isTrigger": false,
						"orientation": {
							"forward": {
								"x": 0.0,
								"y": 0.0,
								"z": 1.0
							},
							"right": {
								"x": 0.852,
								"y": -0.524,
								"z": 0.0
							},
							"up": {
								"x": 0.524,
								"y": 0.852,
								"z": 0.0
							}
						}
					},
					{
						"center": {
							"x": -26.764,
							"y": 29.544,
							"z": 6.404
						},
						"halfExtents": {
							"x": 18.458,
							"y": 0.528,
							"z": 5.731
						},
						"isTrigger": false,
						"orientation": {
							"forward": {
								"x": 0.0,
								"y": 0.0,
								"z": 1.0
							},
							"right": {
								"x": 0.818,
								"y": -0.575,
								"z": 0.0
							},
							"up": {
								"x": 0.575,
								"y": 0.818,
								"z": 0.0
							}
						}
					},
					{
						"center": {
							"x": -28.204,
							"y": 21.933,
							"z": -1.562
						},
						"halfExtents": {
							"x": 12.371,
							"y": 0.5,
							"z": 39.594
						},
						"isTrigger": false,
						"orientation": {
							"forward": {
								"x": 0.0,
								"y": 0.0,
								"z": 1.0
							},
							"right": {
								"x": 1.0,
								"y": 0.0,
								"z": 0.0
							},
							"up": {
								"x": 0.0,
								"y": 1.0,
								"z": 0.0
							}
						}
					},
					{
						"center": {
							"x": -27.291,
							"y": 12.543,
							"z": 22.455
						},
						"halfExtents": {
							"x": 12.803,
							"y": 10.133,
							"z": 0.716
						},
						"isTrigger": false,
						"orientation": {
							"forward": {
								"x": 0.0,
								"y": 0.0,
								"z": 1.0
							},
							"right": {
								"x": 1.0,
								"y": 0.0,
								"z": 0.0
							},
							"up": {
								"x": 0.0,
								"y": 1.0,
								"z": 0.0
							}
						}
					},
					{
						"center": {
							"x": -28.949,
							"y": 9.931,
							"z": -21.796
						},
						"halfExtents": {
							"x": 16.131,
							"y": 11.474,
							"z": 0.5
						},
						"isTrigger": false,
						"orientation": {
							"forward": {
								"x": 0.0,
								"y": 0.0,
								"z": 1.0
							},
							"right": {
								"x": 1.0,
								"y": 0.0,
								"z": 0.0
							},
							"up": {
								"x": 0.0,
								"y": 1.0,
								"z": 0.0
							}
						}
					},
					{
						"center": {
							"x": -16.244,
							"y": 32.653,
							"z": 29.984
						},
						"halfExtents": {
							"x": 0.5,
							"y": 9.972,
							"z": 7.59
						},
						"isTrigger": false,
						"orientation": {
							"forward": {
								"x": 0.0,
								"y": 0.0,
								"z": 1.0
							},
							"right": {
								"x": 1.0,
								"y": 0.0,
								"z": 0.0
							},
							"up": {
								"x": 0.0,
								"y": 1.0,
								"z": 0.0
							}
						}
					},
					{
						"center": {
							"x": -28.299,
							"y": 31.504,
							"z": 38.157
						},
						"halfExtents": {
							"x": 11.612,
							"y": 9.403,
							"z": 0.5
						},
						"isTrigger": false,
						"orientation": {
							"forward": {
								"x": 0.0,
								"y": 0.0,
								"z": 1.0
							},
							"right": {
								"x": 1.0,
								"y": 0.0,
								"z": 0.0
							},
							"up": {
								"x": 0.0,
								"y": 1.0,
								"z": 0.0
							}
						}
					},
					{
						"center": {
							"x": -40.097,
							"y": 32.152,
							"z": 31.602
						},
						"halfExtents": {
							"x": 0.5,
							"y": 9.548,
							"z": 9.082
						},
						"isTrigger": false,
						"orientation": {
							"forward": {
								"x": 0.0,
								"y": 0.0,
								"z": 1.0
							},
							"right": {
								"x": 1.0,
								"y": 0.0,
								"z": 0.0
							},
							"up": {
								"x": 0.0,
								"y": 1.0,
								"z": 0.0
							}
						}
					},
					{
						"center": {
							"x": -28.215,
							"y": 36.882,
							"z": 28.485
						},
						"halfExtents": {
							"x": 10.643,
							"y": 0.5,
							"z": 6.523
						},
						"isTrigger": false,
						"orientation": {
							"forward": {
								"x": 0.0,
								"y": -0.165,
								"z": 0.986
							},
							"right": {
								"x": 1.0,
								"y": 0.0,
								"z": 0.0
							},
							"up": {
								"x": 0.0,
								"y": 0.986,
								"z": 0.165
							}
						}
					},
					{
						"center": {
							"x": 4.445,
							"y": 40.267,
							"z": -10.111
						},
						"halfExtents": {
							"x": 46.919,
							"y": 0.5,
							"z": 10.858
						},
						"isTrigger": false,
						"orientation": {
							"forward": {
								"x": 0.0,
								"y": 0.0,
								"z": 1.0
							},
							"right": {
								"x": 1.0,
								"y": 0.0,
								"z": 0.0
							},
							"up": {
								"x": 0.0,
								"y": 1.0,
								"z": 0.0
							}
						}
					},
					{
						"center": {
							"x": 2.677,
							"y": 50.739,
							"z": 11.086
						},
						"halfExtents": {
							"x": 43.752,
							"y": 0.5,
							"z": 13.905
						},
						"isTrigger": false,
						"orientation": {
							"forward": {
								"x": 0.0,
								"y": -0.622,
								"z": 0.783
							},
							"right": {
								"x": 1.0,
								"y": 0.0,
								"z": 0.0
							},
							"up": {
								"x": 0.0,
								"y": 0.783,
								"z": 0.622
							}
						}
					},
					{
						"center": {
							"x": 2.752,
							"y": 50.337,
							"z": -11.41
						},
						"halfExtents": {
							"x": 44.427,
							"y": 0.5,
							"z": 14.392
						},
						"isTrigger": false,
						"orientation": {
							"forward": {
								"x": 0.0,
								"y": 0.616,
								"z": 0.788
							},
							"right": {
								"x": 1.0,
								"y": 0.0,
								"z": 0.0
							},
							"up": {
								"x": 0.0,
								"y": 0.788,
								"z": -0.616
							}
						}
					},
					{
						"center": {
							"x": -28.158,
							"y": 41.376,
							"z": 22.68
						},
						"halfExtents": {
							"x": 13.505,
							"y": 3.864,
							"z": 0.5
						},
						"isTrigger": false,
						"orientation": {
							"forward": {
								"x": 0.0,
								"y": 0.0,
								"z": 1.0
							},
							"right": {
								"x": 1.0,
								"y": 0.0,
								"z": 0.0
							},
							"up": {
								"x": 0.0,
								"y": 1.0,
								"z": 0.0
							}
						}
					},
					{
						"center": {
							"x": -27.796,
							"y": 28.645,
							"z": -37.675
						},
						"halfExtents": {
							"x": 12.04,
							"y": 7.068,
							"z": 0.5
						},
						"isTrigger": false,
						"orientation": {
							"forward": {
								"x": 0.0,
								"y": 0.0,
								"z": 1.0
							},
							"right": {
								"x": 1.0,
								"y": 0.0,
								"z": 0.0
							},
							"up": {
								"x": 0.0,
								"y": 1.0,
								"z": 0.0
							}
						}
					},
					{
						"center": {
							"x": -16.021,
							"y": 29.759,
							"z": -30.142
						},
						"halfExtents": {
							"x": 0.5,
							"y": 7.92,
							"z": 8.237
						},
						"isTrigger": false,
						"orientation": {
							"forward": {
								"x": 0.0,
								"y": 0.0,
								"z": 1.0
							},
							"right": {
								"x": 1.0,
								"y": 0.0,
								"z": 0.0
							},
							"up": {
								"x": 0.0,
								"y": 1.0,
								"z": 0.0
							}
						}
					},
					{
						"center": {
							"x": -39.636,
							"y": 29.215,
							"z": -31.098
						},
						"halfExtents": {
							"x": 0.5,
							"y": 7.682,
							"z": 9.793
						},
						"isTrigger": false,
						"orientation": {
							"forward": {
								"x": 0.0,
								"y": 0.0,
								"z": 1.0
							},
							"right": {
								"x": 1.0,
								"y": 0.0,
								"z": 0.0
							},
							"up": {
								"x": 0.0,
								"y": 1.0,
								"z": 0.0
							}
						}
					},
					{
						"center": {
							"x": -30.412,
							"y": 36.742,
							"z": -29.02
						},
						"halfExtents": {
							"x": 15.062,
							"y": 0.5,
							"z": 9.18
						},
						"isTrigger": false,
						"orientation": {
							"forward": {
								"x": 0.0,
								"y": 0.167,
								"z": 0.986
							},
							"right": {
								"x": 1.0,
								"y": 0.0,
								"z": 0.0
							},
							"up": {
								"x": 0.0,
								"y": 0.986,
								"z": -0.167
							}
						}
					}
				],
				"interaction": "NONE",
				"static": true
			},
			"transform": {
				"position": {
					"x": 0.0,
					"y": 0.0,
					"z": 0.0
				},
				"rotation": {
					"x": 0.0,
					"y": 0.0,
					"z": 0.0
				},
				"scale": {
					"x": 1.0,
					"y": 1.0,
					"z": 1.0
				}
			}
		},
		{
			"_id": 1,
			"active": true,
			"client": {
				"fragShaderPath": "../resources/shaders/material.frag",
				"isTransparent": false,
				"modelPath": "../resources/objects/cowpen/CowPen.obj",
				"vertShaderPath": "../resources/shaders/material.vert"
			},
			"level": "PENS",
			"name": "CowPen",
			"server": {
				"colliders": [
					{
						"center": {
							"x": -0.249,
							"y": 26.871,
							"z": -35.993
						},
						"halfExtents": {
							"x": 38.726,
							"y": 26.645,
							"z": 0.5
						},
						"isTrigger": false,
						"orientation": {
							"forward": {
								"x": 0.0,
								"y": 0.0,
								"z": 1.0
							},
							"right": {
								"x": 1.0,
								"y": 0.0,
								"z": 0.0
							},
							"up": {
								"x": 0.0,
								"y": 1.0,
								"z": 0.0
							}
						}
					},
					{
						"center": {
							"x": -0.12,
							"y": 25.921,
							"z": 37.083
						},
						"halfExtents": {
							"x": 38.726,
							"y": 26.645,
							"z": 0.5
						},
						"isTrigger": false,
						"orientation": {
							"forward": {
								"x": 0.0,
								"y": 0.0,
								"z": 1.0
							},
							"right": {
								"x": 1.0,
								"y": 0.0,
								"z": 0.0
							},
							"up": {
								"x": 0.0,
								"y": 1.0,
								"z": 0.0
							}
						}
					},
					{
						"center": {
							"x": 38.4,
							"y": 25.143,
							"z": 0.801
						},
						"halfExtents": {
							"x": 0.5,
							"y": 27.665,
							"z": 36.41
						},
						"isTrigger": false,
						"orientation": {
							"forward": {
								"x": 0.0,
								"y": 0.0,
								"z": 1.0
							},
							"right": {
								"x": 1.0,
								"y": 0.0,
								"z": 0.0
							},
							"up": {
								"x": 0.0,
								"y": 1.0,
								"z": 0.0
							}
						}
					},
					{
						"center": {
							"x": -39.219,
							"y": 27.235,
							"z": 1.095
						},
						"halfExtents": {
							"x": 0.5,
							"y": 27.665,
							"z": 36.41
						},
						"isTrigger": false,
						"orientation": {
							"forward": {
								"x": 0.0,
								"y": 0.0,
								"z": 1.0
							},
							"right": {
								"x": 1.0,
								"y": 0.0,
								"z": 0.0
							},
							"up": {
								"x": 0.0,
								"y": 1.0,
								"z": 0.0
							}
						}
					},
					{
						"center": {
							"x": 0.348,
							"y": 0.019,
							"z": 1.084
						},
						"halfExtents": {
							"x": 40.291,
							"y": 0.5,
							"z": 38.602
						},
						"isTrigger": false,
						"orientation": {
							"forward": {
								"x": 0.0,
								"y": 0.0,
								"z": 1.0
							},
							"right": {
								"x": 1.0,
								"y": 0.0,
								"z": 0.0
							},
							"up": {
								"x": 0.0,
								"y": 1.0,
								"z": 0.0
							}
						}
					},
					{
						"center": {
							"x": 17.506,
							"y": 1.677,
							"z": 31.709
						},
						"halfExtents": {
							"x": 7.644,
							"y": 1.519,
							"z": 2.31
						},
						"isTrigger": false,
						"orientation": {
							"forward": {
								"x": 0.0,
								"y": 0.0,
								"z": 1.0
							},
							"right": {
								"x": 1.0,
								"y": 0.0,
								"z": 0.0
							},
							"up": {
								"x": 0.0,
								"y": 1.0,
								"z": 0.0
							}
						}
					},
					{
						"center": {
							"x": -22.122,
							"y": 1.48,
							"z": 16.205
						},
						"halfExtents": {
							"x": 7.644,
							"y": 1.519,
							"z": 2.31
						},
						"isTrigger": false,
						"orientation": {
							"forward": {
								"x": 0.0,
								"y": 0.0,
								"z": 1.0
							},
							"right": {
								"x": 1.0,
								"y": 0.0,
								"z": 0.0
							},
							"up": {
								"x": 0.0,
								"y": 1.0,
								"z": 0.0
							}
						}
					},
					{
						"center": {
							"x": 7.893,
							"y": 1.643,
							"z": -33.482
						},
						"halfExtents": {
							"x": 7.644,
							"y": 1.519,
							"z": 2.31
						},
						"isTrigger": false,
						"orientation": {
							"forward": {
								"x": 0.0,
								"y": 0.0,
								"z": 1.0
							},
							"right": {
								"x": 1.0,
								"y": 0.0,
								"z": 0.0
							},
							"up": {
								"x": 0.0,
								"y": 1.0,
								"z": 0.0
							}
						}
					},
					{
						"center": {
							"x": 0.192,
							"y": 1.355,
							"z": 31.729
						},
						"halfExtents": {
							"x": 5.0,
							"y": 1.611,
							"z": 2.186
						},
						"isTrigger": false,
						"orientation": {
							"forward": {
								"x": 0.0,
								"y": 0.0,
								"z": 1.0
							},
							"right": {
								"x": 1.0,
								"y": 0.0,
								"z": 0.0
							},
							"up": {
								"x": 0.0,
								"y": 1.0,
								"z": 0.0
							}
						}
					},
					{
						"center": {
							"x": 2.913,
							"y": 1.431,
							"z": 0.418
						},
						"halfExtents": {
							"x": 2.5,
							"y": 1.535,
							"z": 2.312
						},
						"isTrigger": false,
						"orientation": {
							"forward": {
								"x": 0.0,
								"y": 0.0,
								"z": 1.0
							},
							"right": {
								"x": 1.0,
								"y": 0.0,
								"z": 0.0
							},
							"up": {
								"x": 0.0,
								"y": 1.0,
								"z": 0.0
							}
						}
					},
					{
						"center": {
							"x": 12.822,
							"y": 1.549,
							"z": -28.469
						},
						"halfExtents": {
							"x": 2.5,
							"y": 1.535,
							"z": 2.312
						},
						"isTrigger": false,
						"orientation": {
							"forward": {
								"x": 0.0,
								"y": 0.0,
								"z": 1.0
							},
							"right": {
								"x": 1.0,
								"y": 0.0,
								"z": 0.0
							},
							"up": {
								"x": 0.0,
								"y": 1.0,
								"z": 0.0
							}
						}
					},
					{
						"center": {
							"x": -16.972,
							"y": 1.68,
							"z": -11.452
						},
						"halfExtents": {
							"x": 2.5,
							"y": 1.535,
							"z": 2.312
						},
						"isTrigger": false,
						"orientation": {
							"forward": {
								"x": 0.0,
								"y": 0.0,
								"z": 1.0
							},
							"right": {
								"x": 1.0,
								"y": 0.0,
								"z": 0.0
							},
							"up": {
								"x": 0.0,
								"y": 1.0,
								"z": 0.0
							}
						}
					},
					{
						"center": {
							"x": -32.639,
							"y": 1.601,
							"z": 11.483
						},
						"halfExtents": {
							"x": 2.5,
							"y": 1.535,
							"z": 2.312
						},
						"isTrigger": false,
						"orientation": {
							"forward": {
								"x": 0.0,
								"y": 0.0,
								"z": 1.0
							},
							"right": {
								"x": 1.0,
								"y": 0.0,
								"z": 0.0
							},
							"up": {
								"x": 0.0,
								"y": 1.0,
								"z": 0.0
							}
						}
					},
					{
						"center": {
							"x": 26.201,
							"y": 0.966,
							"z": -7.043
						},
						"halfExtents": {
							"x": 2.412,
							"y": 2.031,
							"z": 9.881
						},
						"isTrigger": false,
						"orientation": {
							"forward": {
								"x": 0.0,
								"y": 0.0,
								"z": 1.0
							},
							"right": {
								"x": 1.0,
								"y": 0.0,
								"z": 0.0
							},
							"up": {
								"x": 0.0,
								"y": 1.0,
								"z": 0.0
							}
						}
					},
					{
						"center": {
							"x": 18.771,
							"y": 2.705,
							"z": 9.007
						},
						"halfExtents": {
							"x": 20.049,
							"y": 2.5,
							"z": 2.5
						},
						"isTrigger": false,
						"orientation": {
							"forward": {
								"x": 0.0,
								"y": 0.0,
								"z": 1.0
							},
							"right": {
								"x": 1.0,
								"y": 0.0,
								"z": 0.0
							},
							"up": {
								"x": 0.0,
								"y": 1.0,
								"z": 0.0
							}
						}
					},
					{
						"center": {
							"x": 17.512,
							"y": 2.751,
							"z": -26.884
						},
						"halfExtents": {
							"x": 1.574,
							"y": 2.5,
							"z": 8.635
						},
						"isTrigger": false,
						"orientation": {
							"forward": {
								"x": 0.0,
								"y": 0.0,
								"z": 1.0
							},
							"right": {
								"x": 1.0,
								"y": 0.0,
								"z": 0.0
							},
							"up": {
								"x": 0.0,
								"y": 1.0,
								"z": 0.0
							}
						}
					}
				],
				"interaction": "NONE",
				"static": true
			},
			"transform": {
				"position": {
					"x": -12.14,
					"y": 0.0,
					"z": 118.173
				},
				"rotation": {
					"x": 0.0,
					"y": 0.0,
					"z": 0.0
				},
				"scale": {
					"x": 1.0,
					"y": 1.0,
					"z": 1.0
				}
			}
		}
	]
}